{
  "tasks": [
    {
      "id": "5560",
      "todo": "drink water"
    },
    {
      "id": "65ef",
      "task": "DCgdfg"
    },
    {
      "id": "89ef",
      "task": "mihir"
    },
    {
      "id": "f742",
      "task": "12345"
    },
    {
      "id": "b51a",
      "task": "sdf"
    },
    {
      "id": "a30a",
      "task": "sdfa"
    },
    {
      "id": "8eec",
      "task": "dfg"
    },
    {
      "id": "a35b",
      "task": "dgdf"
    },
    {
      "id": "ac1e",
      "task": "sfas"
    }
  ]
}